japy/__init__.py
japy/function_return_value.py
japy/japy_file_scanner.py
japy/japy_function.py
japy/japy_function_wrapper.py
japy/japy_server.py
japy-3.3.dist-info/LICENSE
japy-3.3.dist-info/METADATA
japy-3.3.dist-info/WHEEL
japy-3.3.dist-info/RECORD
